image_analyst/analyzers.py
image_analyst/exceptions.py
image_analyst/image.py
image_analyst/models.py
image_analyst/trackers.py
image_analyst/utils.py
image_analyst-0.2.1.dist-info/LICENSE
image_analyst-0.2.1.dist-info/METADATA
image_analyst-0.2.1.dist-info/WHEEL
image_analyst-0.2.1.dist-info/RECORD
