Metadata-Version: 2.1
Name: image-analyst
Version: 0.2.1
Summary: ImageAnalyst is a library that simplifies image analysis.
Home-page: https://github.com/BergLucas/ImageAnalyst
Keywords: image,analysis
Author: Lucas Berg
Author-email: 55436804+BergLucas@users.noreply.github.com
Requires-Python: >=3.9,<4.0
Classifier: Development Status :: 3 - Alpha
Classifier: License :: OSI Approved :: MIT License
Classifier: Programming Language :: Python :: 3
Classifier: Programming Language :: Python :: 3.9
Classifier: Programming Language :: Python :: 3.10
Classifier: Programming Language :: Python :: 3.11
Provides-Extra: cv2
Provides-Extra: hf
Provides-Extra: onnx
Provides-Extra: tf
Requires-Dist: image-analyst-cv2[cv2] (>=0.2.0,<0.3.0) ; extra == "cv2"
Requires-Dist: image-analyst-hf (>=0.2.0,<0.3.0) ; (python_version >= "3.9" and python_version < "3.12") and (extra == "hf")
Requires-Dist: image-analyst-onnx (>=0.2.0,<0.3.0) ; extra == "onnx"
Requires-Dist: image-analyst-tf (>=0.2.0,<0.3.0) ; (python_version >= "3.9" and python_version < "3.12") and (extra == "tf")
Requires-Dist: numpy (>=1.24.3,<2.0.0)
Project-URL: Repository, https://github.com/BergLucas/ImageAnalyst
